LICENSE
README.md
setup.cfg
setup.py
fitutils/__init__.py
fitutils/fitutils.py
fitutils.egg-info/PKG-INFO
fitutils.egg-info/SOURCES.txt
fitutils.egg-info/dependency_links.txt
fitutils.egg-info/requires.txt
fitutils.egg-info/top_level.txt