Metadata-Version: 2.4
Name: fitutils
Version: 0.3.4
Summary: Utility function and classes for fitting
Home-page: https://https://github.com/M-A-Verdier/Fitutils
Download-URL: https://github.com/M-A-Verdier/Fitutils/archive/v_0.3.4.tar.gz
Author: Marc-Antoine Verdier
Author-email: marc-antoine.verdier@u-paris.fr
License: bsd-3-clause
Keywords: LeastSquare,ErrorBars,Fitting
Classifier: Development Status :: 3 - Alpha
Classifier: Intended Audience :: Developers
Classifier: Topic :: Software Development :: Build Tools
Classifier: License :: OSI Approved :: BSD License
Classifier: Programming Language :: Python :: 3
Classifier: Programming Language :: Python :: 3.4
Classifier: Programming Language :: Python :: 3.5
Classifier: Programming Language :: Python :: 3.6
Classifier: Programming Language :: Python :: 3.7
Classifier: Programming Language :: Python :: 3.8
Classifier: Programming Language :: Python :: 3.9
Classifier: Programming Language :: Python :: 3.10
Classifier: Programming Language :: Python :: 3.11
Classifier: Programming Language :: Python :: 3.12
License-File: LICENSE
Requires-Dist: numpy
Requires-Dist: scipy
Requires-Dist: matplotlib
Dynamic: author
Dynamic: author-email
Dynamic: classifier
Dynamic: download-url
Dynamic: home-page
Dynamic: keywords
Dynamic: license
Dynamic: license-file
Dynamic: requires-dist
Dynamic: summary
